{
	"info": {
		"_postman_id": "865c6be2-105b-4c7a-a963-50a9403eb8f6",
		"name": "Day-4 Task(users)",
		"schema": "https://schema.getpostman.com/json/collection/v2.0.0/collection.json",
		"_exporter_id": "42610088"
	},
	"item": [
		{
			"name": "http://localhost:3000/users",
			"request": {
				"auth": {
					"type": "noauth"
				},
				"method": "POST",
				"header": [],
				"body": {
					"mode": "raw",
					"raw": "{\r\n  \"name\": \"Yashdeep\",\r\n  \"email\": \"yashdeep@example.com\"\r\n}",
					"options": {
						"raw": {
							"language": "json"
						}
					}
				},
				"url": "http://localhost:3000/users"
			},
			"response": []
		},
		{
			"name": "http://localhost:3000/users",
			"protocolProfileBehavior": {
				"disableBodyPruning": true
			},
			"request": {
				"auth": {
					"type": "noauth"
				},
				"method": "GET",
				"header": [],
				"body": {
					"mode": "raw",
					"raw": "{\r\n  \"name\": \"Yashdeep\",\r\n  \"email\": \"yashdeep@example.com\"\r\n}",
					"options": {
						"raw": {
							"language": "json"
						}
					}
				},
				"url": "http://localhost:3000/users"
			},
			"response": []
		},
		{
			"name": "http://localhost:3000/users/1742208475119",
			"request": {
				"auth": {
					"type": "noauth"
				},
				"method": "PUT",
				"header": [],
				"body": {
					"mode": "raw",
					"raw": "{\r\n  \"name\": \"Yashdeep Dabhi\",\r\n  \"email\": \"yashdeepdabhi@example.com\"\r\n}",
					"options": {
						"raw": {
							"language": "json"
						}
					}
				},
				"url": "http://localhost:3000/users/1742208475119"
			},
			"response": []
		},
		{
			"name": "http://localhost:3000/users/1742208475119",
			"request": {
				"auth": {
					"type": "noauth"
				},
				"method": "DELETE",
				"header": [],
				"body": {
					"mode": "raw",
					"raw": "{\r\n  \"name\": \"Yashdeep\",\r\n  \"email\": \"yashdeep@example.com\"\r\n}",
					"options": {
						"raw": {
							"language": "json"
						}
					}
				},
				"url": "http://localhost:3000/users/1742208475119"
			},
			"response": []
		}
	]
}